pyeqx/azure/__init__.py
pyeqx/azure/constants.py
pyeqx/azure/errors.py
pyeqx/azure/helper.py
pyeqx/core/__init__.py
pyeqx/core/common.py
pyeqx/core/configuration.py
pyeqx/core/constants.py
pyeqx/core/errors.py
pyeqx/core/main.py
pyeqx/core/operation.py
pyeqx/core/reader.py
pyeqx/core/retry.py
pyeqx/core/schemas.py
pyeqx/core/writer.py
pyeqx/core/enums/__init__.py
pyeqx/core/enums/data_module_type.py
pyeqx/core/enums/data_type.py
pyeqx/core/models/__init__.py
pyeqx/core/models/app.py
pyeqx/core/models/app_data.py
pyeqx/core/models/app_data_base.py
pyeqx/core/models/app_datas.py
pyeqx/core/models/engine.py
pyeqx/core/models/execution.py
pyeqx/core/models/module/__init__.py
pyeqx/core/models/module/data_module.py
pyeqx/core/models/module/properties/__init__.py
pyeqx/core/models/module/properties/api_data_module_properties.py
pyeqx/core/models/module/properties/data_module_properties.py
pyeqx/core/models/module/properties/database_data_module_properties.py
pyeqx/core/models/module/properties/file_data_module_properties.py
pyeqx/core/models/module/properties/stream_data_module_properties.py
pyeqx/core/models/storage/__init__.py
pyeqx/core/models/storage/data.py
pyeqx/core/models/storage/properties/__init__.py
pyeqx/core/models/storage/properties/api_data_properties.py
pyeqx/core/models/storage/properties/azure_adls_gen_2_storage_data_properties.py
pyeqx/core/models/storage/properties/azure_blob_storage_data_properties.py
pyeqx/core/models/storage/properties/cassandra_data_properties.py
pyeqx/core/models/storage/properties/data_properties.py
pyeqx/core/models/storage/properties/impala_data_properties.py
pyeqx/core/models/storage/properties/kafka_data_properties.py
pyeqx/core/models/storage/properties/local_path_data_properties.py
pyeqx/core/models/storage/properties/mongo_data_properties.py
pyeqx/core/models/storage/properties/mssql_data_properties.py
pyeqx/core/models/storage/properties/nfs_data_properties.py
pyeqx_core-0.7.18.dist-info/METADATA
pyeqx_core-0.7.18.dist-info/WHEEL
pyeqx_core-0.7.18.dist-info/top_level.txt
pyeqx_core-0.7.18.dist-info/RECORD
