Metadata-Version: 2.4
Name: pyeqx-core
Version: 0.7.18
Summary: Python library for interacting with Spark, Azure, Minio, and other data sources.
Author: ESBM Cronus
Classifier: Programming Language :: Python :: 3
Requires-Python: >=3.12
Requires-Dist: adlfs>=2024.8.0
Requires-Dist: azure-identity>=1.25.0
Requires-Dist: azure-storage-blob>=12.26.0
Requires-Dist: azure-storage-file-datalake>=12.21.0
Requires-Dist: azure-storage-queue>=12.13.0
Requires-Dist: boto3>=1.40.36
Requires-Dist: delta-spark<4.0.0,>=3.2.0
Requires-Dist: minio>=7.2.16
Requires-Dist: numpy>=2.3.3
Requires-Dist: pandas>=2.3.2
Requires-Dist: psycopg2-binary>=2.9.10
Requires-Dist: pymssql>=2.3.7
Requires-Dist: pyspark<4.0.0,>=3.5.6
Requires-Dist: requests>=2.32.5
Requires-Dist: tenacity>=9.1.2
Requires-Dist: pyeqx-common>=0.1.1
Provides-Extra: dev
Requires-Dist: black; extra == "dev"
Requires-Dist: ruff; extra == "dev"
Requires-Dist: build; extra == "dev"
Requires-Dist: twine; extra == "dev"
Requires-Dist: python-dotenv; extra == "dev"
Requires-Dist: pytest; extra == "dev"
Requires-Dist: pytest-cov; extra == "dev"
Requires-Dist: pytest-mock; extra == "dev"
Requires-Dist: pytest-watch; extra == "dev"
